<usereventscript scriptid="customscript_uc_ue_emp_changeemployeesub">
  <description></description>
  <isinactive>F</isinactive>
  <name>Change Employee Subsidiary Button</name>
  <notifyadmins>F</notifyadmins>
  <notifyemails>netsuitedevs@compass.com</notifyemails>
  <notifyowner>F</notifyowner>
  <notifyuser>F</notifyuser>
  <scriptfile>[/SuiteScripts/employee/uc_ue_emp_changeemployeesub.js]</scriptfile>
  <scriptdeployments>
    <scriptdeployment scriptid="customdeploy_uc_ue_emp_changeemployeesub">
      <allemployees>F</allemployees>
      <allpartners>F</allpartners>
      <allroles>F</allroles>
      <audslctrole>ADMINISTRATOR</audslctrole>
      <eventtype></eventtype>
      <executeinwebstore>F</executeinwebstore>
      <isdeployed>T</isdeployed>
      <loglevel>DEBUG</loglevel>
      <recordtype>EMPLOYEE</recordtype>
      <runasrole>ADMINISTRATOR</runasrole>
      <status>RELEASED</status>
    </scriptdeployment>
  </scriptdeployments>
</usereventscript>